[
  {
    "groupname": "",
    "header_text": "",
    "footer_text": "",
    "id": null
  },
  {
    "groupname": "nameL6@Ex:\"*",
    "header_text": "headeThi@^tpZ",
    "footer_text": "footH",
    "id": null
  },
  {
    "groupname": "nameT}#(hpn ]",
    "header_text": "headN%Ab<13}92,>79hV",
    "footer_text": "foot uPP",
    "id": null
  },
  {
    "groupname": "name!}IuZ>> Y",
    "header_text": "headp",
    "footer_text": "foot1:O,5Yz:\"~t.rO[50~",
    "id": null
  },
  {
    "groupname": "name",
    "header_text": "head*K\\d*[T;cna   @-4",
    "footer_text": "footD*Gg]>__yct ",
    "id": null
  },
  {
    "groupname": "name",
    "header_text": "headq Ro/",
    "footer_text": "footul, wVxY5\"",
    "id": null
  }
]